dubious_tags/__init__.py
dubious_tags/gen_from_shops.py
dubious_tags/list.py
dubious_tags/unclear_shop_values_with_no_specific_comment.py
dubious_tags-0.0.1.dist-info/METADATA
dubious_tags-0.0.1.dist-info/WHEEL
dubious_tags-0.0.1.dist-info/top_level.txt
dubious_tags-0.0.1.dist-info/RECORD
