Metadata-Version: 2.4
Name: dubious_tags
Version: 0.0.1
Summary: Listing of dubious OSM tags
Home-page: https://codeberg.org/matkoniecz/dubious_tags
Author: Mateusz Konieczny
Author-email: matkoniecz@tutanota.com
License: CC0-1.0
Classifier: Programming Language :: Python :: 3
Classifier: Operating System :: OS Independent
Requires-Dist: taginfo
Requires-Dist: osm_bot_abstraction_layer
Requires-Dist: simple_cache
Dynamic: author
Dynamic: author-email
Dynamic: classifier
Dynamic: description
Dynamic: description-content-type
Dynamic: home-page
Dynamic: license
Dynamic: requires-dist
Dynamic: summary
